CHANGELOG.md
LICENSE
MANIFEST.in
README.rst
requirements.txt
setup.cfg
setup.py
fisk/__init__.py
fisk.egg-info/PKG-INFO
fisk.egg-info/SOURCES.txt
fisk.egg-info/dependency_links.txt
fisk.egg-info/requires.txt
fisk.egg-info/top_level.txt
fisk/CAcerts/demoCAfile.pem
fisk/CAcerts/prodCAfile.pem