Metadata-Version: 1.1
Name: fisk
Version: 0.8.2
Summary: library for fiscalization (Hrvatska) as defined in wsdl-1.1.2 and wsdl-1.2
Home-page: https://github.com/kodmasin/fiskpy
Author: Boris Tomic
Author-email: boris@kodmasin.net
License: Apache Software License
Keywords: fiscalization tax
Platform: UNKNOWN
Classifier: Development Status :: 4 - Beta
Classifier: Environment :: Web Environment
Classifier: Intended Audience :: Developers
Classifier: Intended Audience :: Financial and Insurance Industry
Classifier: Intended Audience :: Information Technology
Classifier: License :: OSI Approved :: Apache Software License
Classifier: Operating System :: OS Independent
Classifier: Programming Language :: Python
Classifier: Programming Language :: Python :: 2
Classifier: Programming Language :: Python :: 2.7
Classifier: Natural Language :: Croatian
Classifier: Topic :: Internet :: WWW/HTTP :: Dynamic Content
Classifier: Topic :: Office/Business :: Financial :: Accounting
Classifier: Topic :: Software Development :: Libraries :: Python Modules
